MANIFEST.in
README
setup.py
src/m3_ext/__init__.py
src/m3_ext/context_processors.py
src/m3_ext/views.py
src/m3_ext/demo/REQUIREMENTS
src/m3_ext/demo/__init__.py
src/m3_ext/demo/app_meta.py
src/m3_ext/demo/actions/__init__.py
src/m3_ext/demo/actions/base.py
src/m3_ext/demo/actions/menus.py
src/m3_ext/demo/actions/sample.py
src/m3_ext/demo/actions/containers/__init__.py
src/m3_ext/demo/actions/containers/conteintertable.py
src/m3_ext/demo/actions/containers/forms.py
src/m3_ext/demo/actions/containers/objectselectionpanel.py
src/m3_ext/demo/actions/fields/__init__.py
src/m3_ext/demo/actions/fields/dictfield.py
src/m3_ext/demo/actions/fields/fields.py
src/m3_ext/demo/actions/fields/searchfield.py
src/m3_ext/demo/actions/fields/uploadfields.py
src/m3_ext/demo/actions/grids/__init__.py
src/m3_ext/demo/actions/grids/grid.py
src/m3_ext/demo/actions/grids/locking_grouping_grid.py
src/m3_ext/demo/actions/grids/multigroupinggrid.py
src/m3_ext/demo/actions/grids/objectgrid.py
src/m3_ext/demo/actions/tree/__init__.py
src/m3_ext/demo/actions/tree/object_tree.py
src/m3_ext/demo/actions/tree/trees.py
src/m3_ext/demo/actions/windows/__init__.py
src/m3_ext/demo/actions/windows/windows.py
src/m3_ext/demo/actions/windows/static/js/demo-edit-window.js
src/m3_ext/demo/actions/windows/static/js/list-window.js
src/m3_ext/demo/actions/windows/static/js/m3-locking-header-group.js
src/m3_ext/gears/__init__.py
src/m3_ext/gears/edit_windows.py
src/m3_ext/static/ext/css/TreeGrid.css
src/m3_ext/static/ext/css/lightbox.css
src/m3_ext/static/ext/images/elbow-end-minus-nl.gif
src/m3_ext/static/ext/images/elbow-end-minus.gif
src/m3_ext/static/ext/images/elbow-end-plus-nl.gif
src/m3_ext/static/ext/images/elbow-end-plus.gif
src/m3_ext/static/ext/images/elbow-end.gif
src/m3_ext/static/ext/images/elbow-line.gif
src/m3_ext/static/ext/images/elbow-minus-nl.gif
src/m3_ext/static/ext/images/elbow-minus.gif
src/m3_ext/static/ext/images/elbow-plus-nl.gif
src/m3_ext/static/ext/images/elbow-plus.gif
src/m3_ui.egg-info/PKG-INFO
src/m3_ui.egg-info/SOURCES.txt
src/m3_ui.egg-info/dependency_links.txt
src/m3_ui.egg-info/top_level.txt