Metadata-Version: 1.1
Name: m3-ui
Version: 3.0.1.5
Summary: UI ExtJS
